{"_ts":[1546319718],"_r":{"breakdown":{"html":{"bytes":[30538],"requests":[2]},"js":{"bytes":[45194],"requests":[3]},"css":{"bytes":[5606],"requests":[1]},"image":{"bytes":[865576],"requests":[13]},"flash":{"bytes":[0],"requests":[0]},"font":{"bytes":[0],"requests":[0]},"video":{"bytes":[0],"requests":[0]},"other":{"bytes":[0],"requests":[0]}},"date":[1546319718],"domElements":[373],"domInteractive":[3015],"firstPaint":[3032.466666663833],"fullyLoaded":[9034.666666666666],"id":["190101_16_1d724c5a1456eb5690e5b1f59a58e9c6"],"loadTime":[7641.666666666667],"render":[3033.3333333333335],"SpeedIndex":[4548],"TTFB":[2078],"videoFrames":[[{"_i":"ms_000000.jpg","_t":0,"_vc":0},{"_i":"ms_003000.jpg","_t":3000,"_vc":39},{"_i":"ms_003100.jpg","_t":3100,"_vc":39},{"_i":"ms_003600.jpg","_t":3600,"_vc":39},{"_i":"ms_003700.jpg","_t":3700,"_vc":39},{"_i":"ms_004100.jpg","_t":4100,"_vc":39},{"_i":"ms_004200.jpg","_t":4200,"_vc":39},{"_i":"ms_004300.jpg","_t":4300,"_vc":39},{"_i":"ms_004400.jpg","_t":4400,"_vc":39},{"_i":"ms_004800.jpg","_t":4800,"_vc":39},{"_i":"ms_005000.jpg","_t":5000,"_vc":39},{"_i":"ms_005300.jpg","_t":5300,"_vc":69},{"_i":"ms_005500.jpg","_t":5500,"_vc":79},{"_i":"ms_005700.jpg","_t":5700,"_vc":100}]],"visualComplete":[5766.666666666667],"lighthouse":[57],"pagespeed":[91]}}