{"_ts":[1577841539],"_r":{"breakdown":{"html":{"bytes":[10706],"requests":[1]},"js":{"bytes":[44459],"requests":[3]},"css":{"bytes":[7582],"requests":[1]},"image":{"bytes":[0],"requests":[0]},"flash":{"bytes":[0],"requests":[0]},"font":{"bytes":[0],"requests":[0]},"video":{"bytes":[0],"requests":[0]},"other":{"bytes":[0],"requests":[0]}},"date":[1577841539],"domElements":[211],"domInteractive":[2837.6666666666665],"firstPaint":[2869.1449999993333],"fullyLoaded":[3385.6666666666665],"id":["200101_ZR_1ae8f1d10fab78d967b891aa4d559045"],"loadTime":[2863],"render":[2833.3333333333335],"SpeedIndex":[2834],"TTFB":[1770.6666666666667],"videoFrames":[[{"_i":"ms_000000.jpg","_t":0,"_vc":0},{"_i":"ms_002700.jpg","_t":2700,"_vc":100}]],"visualComplete":[2866.6666666666665],"lighthouse":[54],"pagespeed":[89]}}