{"_ts":[1554163757,1554249903],"_r":{"breakdown":{"html":{"bytes":[2597,2597],"requests":[1,1]},"js":{"bytes":[0,0],"requests":[0,0]},"css":{"bytes":[0,0],"requests":[0,0]},"image":{"bytes":[623562,623562],"requests":[2,2]},"flash":{"bytes":[0,0],"requests":[0,0]},"font":{"bytes":[0,0],"requests":[0,0]},"video":{"bytes":[0,0],"requests":[0,0]},"other":{"bytes":[0,0],"requests":[0,0]}},"date":[1554163757,1554249903],"domElements":[73,73],"domInteractive":[1636,1680],"firstPaint":[1703.0300000006,1746.3349999998],"fullyLoaded":[6244,6236],"id":["190401_8Y_4529a0ed003064f6864ee1e6a4939b51","190402_6P_caa6f2cb2ef375f61d250895035dee66"],"loadTime":[5889,5891],"render":[1800,1800],"SpeedIndex":[1987,2073],"TTFB":[1618,1660],"videoFrames":[[{"_i":"ms_000000.jpg","_t":0,"_vc":0},{"_i":"ms_001800.jpg","_t":1800,"_vc":79},{"_i":"ms_002400.jpg","_t":2400,"_vc":89},{"_i":"ms_002900.jpg","_t":2900,"_vc":99},{"_i":"ms_003100.jpg","_t":3100,"_vc":99},{"_i":"ms_003200.jpg","_t":3200,"_vc":99},{"_i":"ms_003500.jpg","_t":3500,"_vc":100},{"_i":"ms_003600.jpg","_t":3600,"_vc":100},{"_i":"ms_004500.jpg","_t":4500,"_vc":100},{"_i":"ms_005500.jpg","_t":5500,"_vc":100},{"_i":"ms_005900.jpg","_t":5900,"_vc":100}],[{"_i":"ms_000000.jpg","_t":0,"_vc":0},{"_i":"ms_001800.jpg","_t":1800,"_vc":79},{"_i":"ms_002400.jpg","_t":2400,"_vc":89},{"_i":"ms_003100.jpg","_t":3100,"_vc":90},{"_i":"ms_003200.jpg","_t":3200,"_vc":90},{"_i":"ms_003500.jpg","_t":3500,"_vc":90},{"_i":"ms_003800.jpg","_t":3800,"_vc":100},{"_i":"ms_004500.jpg","_t":4500,"_vc":100},{"_i":"ms_004900.jpg","_t":4900,"_vc":100},{"_i":"ms_005500.jpg","_t":5500,"_vc":100},{"_i":"ms_005900.jpg","_t":5900,"_vc":100},{"_i":"ms_006000.jpg","_t":6000,"_vc":100}]],"visualComplete":[3500,3800],"lighthouse":[57,57],"pagespeed":[97,97]}}