{"_ts":[1533101885,1533189128],"_r":{"breakdown":{"html":{"bytes":[1665,2113],"requests":[1,1]},"js":{"bytes":[0,0],"requests":[0,0]},"css":{"bytes":[0,0],"requests":[0,0]},"image":{"bytes":[11082,11082],"requests":[1,1]},"flash":{"bytes":[0,0],"requests":[0,0]},"font":{"bytes":[0,0],"requests":[0,0]},"video":{"bytes":[0,0],"requests":[0,0]},"other":{"bytes":[0,0],"requests":[0,0]}},"date":[1533101885,1533189128],"domElements":[23,23],"domInteractive":[1576,1533],"firstPaint":[1595.4666666706,1559.4999999982],"fullyLoaded":[2317.3333333333,2273],"id":["180801_X4_aaea93d6e3417c8c4110c790f8bd9e10","180802_KW_4ae51fa4f79fb5a3bcebdff9fdbc6787"],"loadTime":[1978,1934.3333333333],"render":[1566.6666666667,1566.6666666667],"SpeedIndex":[1718.6666666667,1714.6666666667],"TTFB":[1567.6666666667,1521],"videoFrames":[[{"_i":"ms_000000.jpg","_t":0,"_vc":0},{"_i":"ms_001600.jpg","_t":1600,"_vc":62},{"_i":"ms_002000.jpg","_t":2000,"_vc":100}],[{"_i":"ms_000000.jpg","_t":0,"_vc":0},{"_i":"ms_001600.jpg","_t":1600,"_vc":63},{"_i":"ms_002000.jpg","_t":2000,"_vc":100}]],"visualComplete":[1966.6666666667,1966.6666666667],"lighthouse":[57,57],"pagespeed":[100,100]}}